kgen/K_functions.py
kgen/__init__.py
kgen/coefs.py
kgen/coefficients/K_calculation.json
kgen/coefficients/K_pressure_correction.json
kgen/coefficients/fundamental_constants.json
kgen-1.0.1.dist-info/METADATA
kgen-1.0.1.dist-info/WHEEL
kgen-1.0.1.dist-info/top_level.txt
kgen-1.0.1.dist-info/RECORD
