Metadata-Version: 2.4
Name: Kgen
Version: 1.0.1
Summary: Python functions for calculating stoichiometric speciation constants for seawater.
Author-email: Oscar Branson <ob266@cam.ac.uk>, Ross Whiteford <Ross.Whiteford@rhul.ac.uk>, Dennis Mayk <dm807@cantab.ac.uk>
License-Expression: MIT
Project-URL: Homepage, https://github.com/PalaeoCarbonateChemistry/Kgen
Project-URL: PalaeoCarbonateChemistry, https://github.com/PalaeoCarbonateChemistry
Classifier: Programming Language :: Python :: 3
Requires-Dist: numpy>=1.21.5
Requires-Dist: pymyami==2.1.1
